Metadata-Version: 1.0
Name: packaging-python-tuto-guillaume
Version: 0.1
Summary: A random lib to test packaging
Home-page: http://github.com/storborg/funniest
Author: Guillaume GUILLET
Author-email: guillaume.guillet@ripplemotion.fr
License: UNKNOWN
Platform: UNKNOWN
